{
  "worldName": "grid",
  "options": {
    "imageURL": "textures/maps/grid.png",
    "groundType": "box",
    "length": 400,
    "width": 400,
    "uScale": 20,
    "vScale": 20,
    "imageScale": "2.353",
    "timer": "none",
    "timerDuration": 60,
    "timerEnd": "continue",
    "wall": true,
    "wallHeight": 10,
    "wallThickness": 5,
    "wallColor": "B3B3B3",
    "groundFriction": 1,
    "wallFriction": 0.1,
    "groundRestitution": 0,
    "wallRestitution": 0.1,
    "restartAnimationOnRun": false,
    "objects": [],
    "startPos": "center",
    "startPosXYZStr": "",
    "startRotStr": "",
    "startPosXYZ": null,
    "startRot": null,
    "arenaStartPosXYZ": null,
    "arenaStartRot": null
  }
}